davinci_remote_video_player-0.0.1.dist-info/licenses/LICENSE
dvplayer/__init__.py
dvplayer/dvplayer.py
davinci_remote_video_player-0.0.1.dist-info/METADATA
davinci_remote_video_player-0.0.1.dist-info/WHEEL
davinci_remote_video_player-0.0.1.dist-info/entry_points.txt
davinci_remote_video_player-0.0.1.dist-info/top_level.txt
davinci_remote_video_player-0.0.1.dist-info/RECORD
