Metadata-Version: 2.4
Name: davinci-remote-video-player
Version: 0.0.1
Summary: A simple CLI tool for playing video files on remote HPC clusters
Author: Leonardo Baroncelli
License: MIT
Project-URL: Homepage, https://github.com/LeoBaro/remote-video-player
Project-URL: Issues, https://github.com/LeoBaro/remote-video-player/issues
Keywords: video,player,hpc,remote,opencv
Classifier: Development Status :: 3 - Alpha
Classifier: Intended Audience :: Developers
Classifier: Intended Audience :: Science/Research
Classifier: License :: OSI Approved :: MIT License
Classifier: Programming Language :: Python :: 3
Classifier: Programming Language :: Python :: 3.7
Classifier: Programming Language :: Python :: 3.8
Classifier: Programming Language :: Python :: 3.9
Classifier: Programming Language :: Python :: 3.10
Classifier: Programming Language :: Python :: 3.11
Classifier: Topic :: Multimedia :: Video :: Display
Requires-Python: >=3.7
License-File: LICENSE
Requires-Dist: opencv-python>=4.5.0
Requires-Dist: tqdm>=4.0.0
Dynamic: license-file
